<?xml version="1.0"?>
<property-set xmlns="http://mcc.lip6.fr/">
  <property>
    <id>Diffusion2D-PT-D10N010-00</id>
    <description>Automatically generated</description>
    <formula>
      <all-paths>
        <negation>
          <until>
            <before>
              <conjunction>
                <integer-le>
                  <integer-constant>0</integer-constant>
                  <tokens-count>
                    <place>cAMP__4_6_</place>
                  </tokens-count>
                </integer-le>
                <finally>
                  <next>
                    <disjunction>
                      <integer-le>
                        <integer-constant>3</integer-constant>
                        <tokens-count>
                          <place>cAMP__4_8_</place>
                        </tokens-count>
                      </integer-le>
                      <integer-le>
                        <integer-constant>0</integer-constant>
                        <tokens-count>
                          <place>cAMP__4_6_</place>
                        </tokens-count>
                      </integer-le>
                    </disjunction>
                  </next>
                </finally>
                <until>
                  <before>
                    <integer-le>
                      <tokens-count>
                        <place>cAMP__3_3_</place>
                      </tokens-count>
                      <tokens-count>
                        <place>cAMP__4_8_</place>
                      </tokens-count>
                    </integer-le>
                  </before>
                  <reach>
                    <next>
                      <integer-le>
                        <tokens-count>
                          <place>cAMP__3_3_</place>
                        </tokens-count>
                        <tokens-count>
                          <place>cAMP__4_8_</place>
                        </tokens-count>
                      </integer-le>
                    </next>
                  </reach>
                </until>
              </conjunction>
            </before>
            <reach>
              <integer-le>
                <integer-constant>3</integer-constant>
                <tokens-count>
                  <place>cAMP__4_8_</place>
                </tokens-count>
              </integer-le>
            </reach>
          </until>
        </negation>
      </all-paths>
    </formula>
  </property>
  <property>
    <id>Diffusion2D-PT-D10N010-01</id>
    <description>Automatically generated</description>
    <formula>
      <all-paths>
        <disjunction>
          <finally>
            <until>
              <before>
                <globally>
                  <finally>
                    <integer-le>
                      <tokens-count>
                        <place>cAMP__7_9_</place>
                      </tokens-count>
                      <tokens-count>
                        <place>cAMP__1_8_</place>
                      </tokens-count>
                    </integer-le>
                  </finally>
                </globally>
              </before>
              <reach>
                <integer-le>
                  <integer-constant>2</integer-constant>
                  <tokens-count>
                    <place>cAMP__1_10_</place>
                  </tokens-count>
                </integer-le>
              </reach>
            </until>
          </finally>
          <globally>
            <negation>
              <next>
                <finally>
                  <integer-le>
                    <integer-constant>3</integer-constant>
                    <tokens-count>
                      <place>cAMP__7_2_</place>
                    </tokens-count>
                  </integer-le>
                </finally>
              </next>
            </negation>
          </globally>
        </disjunction>
      </all-paths>
    </formula>
  </property>
  <property>
    <id>Diffusion2D-PT-D10N010-02</id>
    <description>Automatically generated</description>
    <formula>
      <all-paths>
        <globally>
          <until>
            <before>
              <until>
                <before>
                  <disjunction>
                    <integer-le>
                      <tokens-count>
                        <place>cAMP__4_10_</place>
                      </tokens-count>
                      <tokens-count>
                        <place>cAMP__2_6_</place>
                      </tokens-count>
                    </integer-le>
                    <next>
                      <negation>
                        <globally>
                          <until>
                            <before>
                              <negation>
                                <integer-le>
                                  <tokens-count>
                                    <place>cAMP__4_10_</place>
                                  </tokens-count>
                                  <tokens-count>
                                    <place>cAMP__2_6_</place>
                                  </tokens-count>
                                </integer-le>
                              </negation>
                            </before>
                            <reach>
                              <integer-le>
                                <integer-constant>1</integer-constant>
                                <tokens-count>
                                  <place>cAMP__8_6_</place>
                                </tokens-count>
                              </integer-le>
                            </reach>
                          </until>
                        </globally>
                      </negation>
                    </next>
                  </disjunction>
                </before>
                <reach>
                  <globally>
                    <integer-le>
                      <tokens-count>
                        <place>cAMP__9_3_</place>
                      </tokens-count>
                      <tokens-count>
                        <place>cAMP__3_5_</place>
                      </tokens-count>
                    </integer-le>
                  </globally>
                </reach>
              </until>
            </before>
            <reach>
              <integer-le>
                <integer-constant>2</integer-constant>
                <tokens-count>
                  <place>cAMP__2_1_</place>
                </tokens-count>
              </integer-le>
            </reach>
          </until>
        </globally>
      </all-paths>
    </formula>
  </property>
  <property>
    <id>Diffusion2D-PT-D10N010-03</id>
    <description>Automatically generated</description>
    <formula>
      <all-paths>
        <globally>
          <until>
            <before>
              <integer-le>
                <integer-constant>3</integer-constant>
                <tokens-count>
                  <place>cAMP__8_4_</place>
                </tokens-count>
              </integer-le>
            </before>
            <reach>
              <integer-le>
                <tokens-count>
                  <place>cAMP__7_6_</place>
                </tokens-count>
                <tokens-count>
                  <place>cAMP__6_8_</place>
                </tokens-count>
              </integer-le>
            </reach>
          </until>
        </globally>
      </all-paths>
    </formula>
  </property>
  <property>
    <id>Diffusion2D-PT-D10N010-04</id>
    <description>Automatically generated</description>
    <formula>
      <all-paths>
        <globally>
          <finally>
            <next>
              <globally>
                <finally>
                  <disjunction>
                    <finally>
                      <integer-le>
                        <integer-constant>1</integer-constant>
                        <tokens-count>
                          <place>cAMP__5_8_</place>
                        </tokens-count>
                      </integer-le>
                    </finally>
                    <finally>
                      <globally>
                        <integer-le>
                          <integer-constant>2</integer-constant>
                          <tokens-count>
                            <place>cAMP__3_10_</place>
                          </tokens-count>
                        </integer-le>
                      </globally>
                    </finally>
                  </disjunction>
                </finally>
              </globally>
            </next>
          </finally>
        </globally>
      </all-paths>
    </formula>
  </property>
  <property>
    <id>Diffusion2D-PT-D10N010-05</id>
    <description>Automatically generated</description>
    <formula>
      <all-paths>
        <next>
          <until>
            <before>
              <until>
                <before>
                  <next>
                    <integer-le>
                      <tokens-count>
                        <place>cAMP__4_1_</place>
                      </tokens-count>
                      <tokens-count>
                        <place>cAMP__5_10_</place>
                      </tokens-count>
                    </integer-le>
                  </next>
                </before>
                <reach>
                  <integer-le>
                    <tokens-count>
                      <place>cAMP__2_7_</place>
                    </tokens-count>
                    <tokens-count>
                      <place>cAMP__6_5_</place>
                    </tokens-count>
                  </integer-le>
                </reach>
              </until>
            </before>
            <reach>
              <next>
                <negation>
                  <conjunction>
                    <integer-le>
                      <tokens-count>
                        <place>cAMP__7_9_</place>
                      </tokens-count>
                      <tokens-count>
                        <place>cAMP__8_8_</place>
                      </tokens-count>
                    </integer-le>
                    <globally>
                      <finally>
                        <integer-le>
                          <tokens-count>
                            <place>cAMP__3_4_</place>
                          </tokens-count>
                          <tokens-count>
                            <place>cAMP__6_4_</place>
                          </tokens-count>
                        </integer-le>
                      </finally>
                    </globally>
                  </conjunction>
                </negation>
              </next>
            </reach>
          </until>
        </next>
      </all-paths>
    </formula>
  </property>
  <property>
    <id>Diffusion2D-PT-D10N010-06</id>
    <description>Automatically generated</description>
    <formula>
      <all-paths>
        <next>
          <disjunction>
            <finally>
              <integer-le>
                <integer-constant>1</integer-constant>
                <tokens-count>
                  <place>cAMP__9_5_</place>
                </tokens-count>
              </integer-le>
            </finally>
            <globally>
              <until>
                <before>
                  <finally>
                    <disjunction>
                      <integer-le>
                        <tokens-count>
                          <place>cAMP__3_5_</place>
                        </tokens-count>
                        <tokens-count>
                          <place>cAMP__9_3_</place>
                        </tokens-count>
                      </integer-le>
                      <integer-le>
                        <integer-constant>0</integer-constant>
                        <tokens-count>
                          <place>cAMP__1_1_</place>
                        </tokens-count>
                      </integer-le>
                    </disjunction>
                  </finally>
                </before>
                <reach>
                  <next>
                    <globally>
                      <integer-le>
                        <tokens-count>
                          <place>cAMP__3_2_</place>
                        </tokens-count>
                        <tokens-count>
                          <place>cAMP__5_1_</place>
                        </tokens-count>
                      </integer-le>
                    </globally>
                  </next>
                </reach>
              </until>
            </globally>
          </disjunction>
        </next>
      </all-paths>
    </formula>
  </property>
  <property>
    <id>Diffusion2D-PT-D10N010-07</id>
    <description>Automatically generated</description>
    <formula>
      <all-paths>
        <next>
          <conjunction>
            <next>
              <globally>
                <next>
                  <next>
                    <next>
                      <integer-le>
                        <integer-constant>2</integer-constant>
                        <tokens-count>
                          <place>cAMP__6_8_</place>
                        </tokens-count>
                      </integer-le>
                    </next>
                  </next>
                </next>
              </globally>
            </next>
            <negation>
              <globally>
                <integer-le>
                  <tokens-count>
                    <place>cAMP__2_6_</place>
                  </tokens-count>
                  <tokens-count>
                    <place>cAMP__6_6_</place>
                  </tokens-count>
                </integer-le>
              </globally>
            </negation>
          </conjunction>
        </next>
      </all-paths>
    </formula>
  </property>
  <property>
    <id>Diffusion2D-PT-D10N010-08</id>
    <description>Automatically generated</description>
    <formula>
      <all-paths>
        <globally>
          <negation>
            <integer-le>
              <integer-constant>0</integer-constant>
              <tokens-count>
                <place>cAMP__4_6_</place>
              </tokens-count>
            </integer-le>
          </negation>
        </globally>
      </all-paths>
    </formula>
  </property>
  <property>
    <id>Diffusion2D-PT-D10N010-09</id>
    <description>Automatically generated</description>
    <formula>
      <all-paths>
        <negation>
          <finally>
            <until>
              <before>
                <next>
                  <integer-le>
                    <integer-constant>3</integer-constant>
                    <tokens-count>
                      <place>cAMP__9_7_</place>
                    </tokens-count>
                  </integer-le>
                </next>
              </before>
              <reach>
                <finally>
                  <until>
                    <before>
                      <integer-le>
                        <integer-constant>2</integer-constant>
                        <tokens-count>
                          <place>cAMP__6_10_</place>
                        </tokens-count>
                      </integer-le>
                    </before>
                    <reach>
                      <conjunction>
                        <integer-le>
                          <tokens-count>
                            <place>cAMP__5_10_</place>
                          </tokens-count>
                          <tokens-count>
                            <place>cAMP__4_8_</place>
                          </tokens-count>
                        </integer-le>
                        <negation>
                          <integer-le>
                            <integer-constant>3</integer-constant>
                            <tokens-count>
                              <place>cAMP__9_7_</place>
                            </tokens-count>
                          </integer-le>
                        </negation>
                      </conjunction>
                    </reach>
                  </until>
                </finally>
              </reach>
            </until>
          </finally>
        </negation>
      </all-paths>
    </formula>
  </property>
  <property>
    <id>Diffusion2D-PT-D10N010-10</id>
    <description>Automatically generated</description>
    <formula>
      <all-paths>
        <next>
          <disjunction>
            <finally>
              <integer-le>
                <integer-constant>2</integer-constant>
                <tokens-count>
                  <place>cAMP__7_9_</place>
                </tokens-count>
              </integer-le>
            </finally>
            <negation>
              <until>
                <before>
                  <finally>
                    <integer-le>
                      <integer-constant>2</integer-constant>
                      <tokens-count>
                        <place>cAMP__7_9_</place>
                      </tokens-count>
                    </integer-le>
                  </finally>
                </before>
                <reach>
                  <disjunction>
                    <globally>
                      <integer-le>
                        <tokens-count>
                          <place>cAMP__1_4_</place>
                        </tokens-count>
                        <tokens-count>
                          <place>cAMP__5_5_</place>
                        </tokens-count>
                      </integer-le>
                    </globally>
                    <next>
                      <integer-le>
                        <tokens-count>
                          <place>cAMP__2_10_</place>
                        </tokens-count>
                        <tokens-count>
                          <place>cAMP__3_3_</place>
                        </tokens-count>
                      </integer-le>
                    </next>
                  </disjunction>
                </reach>
              </until>
            </negation>
          </disjunction>
        </next>
      </all-paths>
    </formula>
  </property>
  <property>
    <id>Diffusion2D-PT-D10N010-11</id>
    <description>Automatically generated</description>
    <formula>
      <all-paths>
        <disjunction>
          <integer-le>
            <tokens-count>
              <place>cAMP__4_6_</place>
            </tokens-count>
            <tokens-count>
              <place>cAMP__9_10_</place>
            </tokens-count>
          </integer-le>
          <integer-le>
            <integer-constant>3</integer-constant>
            <tokens-count>
              <place>cAMP__8_10_</place>
            </tokens-count>
          </integer-le>
          <finally>
            <integer-le>
              <integer-constant>3</integer-constant>
              <tokens-count>
                <place>cAMP__8_10_</place>
              </tokens-count>
            </integer-le>
          </finally>
          <conjunction>
            <finally>
              <integer-le>
                <integer-constant>3</integer-constant>
                <tokens-count>
                  <place>cAMP__8_10_</place>
                </tokens-count>
              </integer-le>
            </finally>
            <globally>
              <integer-le>
                <integer-constant>2</integer-constant>
                <tokens-count>
                  <place>cAMP__5_2_</place>
                </tokens-count>
              </integer-le>
            </globally>
          </conjunction>
        </disjunction>
      </all-paths>
    </formula>
  </property>
  <property>
    <id>Diffusion2D-PT-D10N010-12</id>
    <description>Automatically generated</description>
    <formula>
      <all-paths>
        <conjunction>
          <integer-le>
            <tokens-count>
              <place>cAMP__1_3_</place>
            </tokens-count>
            <tokens-count>
              <place>cAMP__3_8_</place>
            </tokens-count>
          </integer-le>
          <integer-le>
            <integer-constant>2</integer-constant>
            <tokens-count>
              <place>cAMP__4_3_</place>
            </tokens-count>
          </integer-le>
          <globally>
            <finally>
              <globally>
                <next>
                  <disjunction>
                    <integer-le>
                      <tokens-count>
                        <place>cAMP__1_3_</place>
                      </tokens-count>
                      <tokens-count>
                        <place>cAMP__3_8_</place>
                      </tokens-count>
                    </integer-le>
                    <integer-le>
                      <tokens-count>
                        <place>cAMP__10_4_</place>
                      </tokens-count>
                      <tokens-count>
                        <place>cAMP__1_8_</place>
                      </tokens-count>
                    </integer-le>
                  </disjunction>
                </next>
              </globally>
            </finally>
          </globally>
        </conjunction>
      </all-paths>
    </formula>
  </property>
  <property>
    <id>Diffusion2D-PT-D10N010-13</id>
    <description>Automatically generated</description>
    <formula>
      <all-paths>
        <conjunction>
          <finally>
            <globally>
              <until>
                <before>
                  <integer-le>
                    <integer-constant>0</integer-constant>
                    <tokens-count>
                      <place>cAMP__8_9_</place>
                    </tokens-count>
                  </integer-le>
                </before>
                <reach>
                  <finally>
                    <next>
                      <integer-le>
                        <tokens-count>
                          <place>cAMP__1_7_</place>
                        </tokens-count>
                        <tokens-count>
                          <place>cAMP__9_2_</place>
                        </tokens-count>
                      </integer-le>
                    </next>
                  </finally>
                </reach>
              </until>
            </globally>
          </finally>
          <finally>
            <negation>
              <integer-le>
                <tokens-count>
                  <place>cAMP__9_5_</place>
                </tokens-count>
                <tokens-count>
                  <place>cAMP__7_10_</place>
                </tokens-count>
              </integer-le>
            </negation>
          </finally>
        </conjunction>
      </all-paths>
    </formula>
  </property>
  <property>
    <id>Diffusion2D-PT-D10N010-14</id>
    <description>Automatically generated</description>
    <formula>
      <all-paths>
        <negation>
          <conjunction>
            <globally>
              <integer-le>
                <tokens-count>
                  <place>cAMP__10_6_</place>
                </tokens-count>
                <tokens-count>
                  <place>cAMP__10_1_</place>
                </tokens-count>
              </integer-le>
            </globally>
            <next>
              <until>
                <before>
                  <integer-le>
                    <integer-constant>3</integer-constant>
                    <tokens-count>
                      <place>cAMP__5_5_</place>
                    </tokens-count>
                  </integer-le>
                </before>
                <reach>
                  <until>
                    <before>
                      <integer-le>
                        <integer-constant>3</integer-constant>
                        <tokens-count>
                          <place>cAMP__10_4_</place>
                        </tokens-count>
                      </integer-le>
                    </before>
                    <reach>
                      <integer-le>
                        <tokens-count>
                          <place>cAMP__2_7_</place>
                        </tokens-count>
                        <tokens-count>
                          <place>cAMP__5_10_</place>
                        </tokens-count>
                      </integer-le>
                    </reach>
                  </until>
                </reach>
              </until>
            </next>
          </conjunction>
        </negation>
      </all-paths>
    </formula>
  </property>
  <property>
    <id>Diffusion2D-PT-D10N010-15</id>
    <description>Automatically generated</description>
    <formula>
      <all-paths>
        <conjunction>
          <next>
            <integer-le>
              <integer-constant>1</integer-constant>
              <tokens-count>
                <place>cAMP__3_7_</place>
              </tokens-count>
            </integer-le>
          </next>
          <next>
            <next>
              <integer-le>
                <integer-constant>1</integer-constant>
                <tokens-count>
                  <place>cAMP__5_8_</place>
                </tokens-count>
              </integer-le>
            </next>
          </next>
          <next>
            <next>
              <finally>
                <integer-le>
                  <integer-constant>1</integer-constant>
                  <tokens-count>
                    <place>cAMP__3_7_</place>
                  </tokens-count>
                </integer-le>
              </finally>
            </next>
          </next>
        </conjunction>
      </all-paths>
    </formula>
  </property>
</property-set>
